<annotation>
	<folder>Test Images</folder>
	<filename>39.jpg</filename>
	<path>C:\Users\sarma\Pictures\Camera Roll\Test Images\39.jpg</path>
	<source>
		<database>Unknown</database>
	</source>
	<size>
		<width>640</width>
		<height>480</height>
		<depth>3</depth>
	</size>
	<segmented>0</segmented>
	<object>
		<name>Agent</name>
		<pose>Unspecified</pose>
		<truncated>0</truncated>
		<difficult>0</difficult>
		<bndbox>
			<xmin>221</xmin>
			<ymin>169</ymin>
			<xmax>251</xmax>
			<ymax>207</ymax>
		</bndbox>
	</object>
	<object>
		<name>Agent</name>
		<pose>Unspecified</pose>
		<truncated>0</truncated>
		<difficult>0</difficult>
		<bndbox>
			<xmin>415</xmin>
			<ymin>158</ymin>
			<xmax>460</xmax>
			<ymax>188</ymax>
		</bndbox>
	</object>
</annotation>
